pygam/__init__.py
pygam/callbacks.py
pygam/core.py
pygam/distributions.py
pygam/links.py
pygam/penalties.py
pygam/pygam.py
pygam/terms.py
pygam/utils.py
pygam/datasets/__init__.py
pygam/datasets/blood1.csv
pygam/datasets/cake.csv
pygam/datasets/chicago.csv
pygam/datasets/coal.csv
pygam/datasets/default.csv
pygam/datasets/faithful.csv
pygam/datasets/head_circumference.csv
pygam/datasets/hepatitis_A_bulgaria.csv
pygam/datasets/load_datasets.py
pygam/datasets/mcycle.csv
pygam/datasets/trees.csv
pygam/datasets/wage.csv
pygamfast-0.10.0.dist-info/LICENSE
pygamfast-0.10.0.dist-info/WHEEL
pygamfast-0.10.0.dist-info/METADATA
pygamfast-0.10.0.dist-info/RECORD
